baltic/__init__.py
baltic/baltic.py
baltic/samogitia.py
baltic-0.2.2.dist-info/LICENSE
baltic-0.2.2.dist-info/METADATA
baltic-0.2.2.dist-info/WHEEL
baltic-0.2.2.dist-info/top_level.txt
baltic-0.2.2.dist-info/RECORD
