Metadata-Version: 2.1
Name: baltic
Version: 0.2.2
Summary: Lightweight package for analyzing, manipulating and visualizing annotated phylogenetic trees
Home-page: https://github.com/evogytis/baltic
Download-URL: https://github.com/evogytis/baltic/archive/v0.2.2.tar.gz
Author: Gytis Dudas
Author-email: gytisdudas@gmail.com
License: gpl-3.0
Keywords: phylogeny,visualization
Requires-Python: >=3.5
License-File: LICENSE
